quant_risk_mgmt/__init__.py
quant_risk_mgmt/riskmgmlib.py
quant_risk_mgmt-1.0.1.dist-info/METADATA
quant_risk_mgmt-1.0.1.dist-info/WHEEL
quant_risk_mgmt-1.0.1.dist-info/RECORD
