Metadata-Version: 2.1
Name: quant_risk_mgmt
Version: 1.0.1
Summary: Package for quant risk management, with wide range of functions including fixing PSD, VaR and ES, etc.
Project-URL: Homepage, https://github.com/xiaokuan-zhao/FINTECH545
Project-URL: Bug Tracker, https://github.com/xiaokuan-zhao/FINTECH545/issues
Author-email: Xiaokuan Zhao <xiaokuanzhao@gmail.com>
Classifier: License :: OSI Approved :: MIT License
Classifier: Operating System :: OS Independent
Classifier: Programming Language :: Python :: 3
Requires-Python: >=3.7
